{
    "6219318306": {
        "balance": 0,
        "cards": {
            "Лечинк... Стоп а где он?": {
                "last_used": 1764176777.6570573,
                "rarity": "Обычный",
                "points_earned": 50,
                "coins_earned": 5
            }
        },
        "points": 50,
        "coins": 5,
        "nickname": "Fox",
        "inventory": {
            "luck_booster": 0,
            "time_booster": 0
        },
        "active_luck": false,
        "last_card": "Лечинк... Стоп а где он?"
    },
    "5414350766": {
        "balance": 0,
        "cards": {
            "Простой Лечинка": {
                "last_used": 1764176778.4926884,
                "rarity": "Обычный",
                "points_earned": 50,
                "coins_earned": 5
            },
            "Лечинкель в магазине": {
                "last_used": 1764344270.8779595,
                "rarity": "Обычный",
                "points_earned": 50,
                "coins_earned": 5
            }
        },
        "points": 100,
        "coins": 10,
        "nickname": "Ne_yrarikkon",
        "inventory": {
            "luck_booster": 0,
            "time_booster": 0
        },
        "active_luck": false,
        "last_card": "Лечинкель в магазине"
    },
    "7551062449": {
        "balance": 0,
        "cards": {
            "Культурный ле чинкель": {
                "last_used": 1764176782.4130254,
                "rarity": "Обычный",
                "points_earned": 50,
                "coins_earned": 5
            },
            "Верой Лечинкель": {
                "last_used": 1764344305.5060196,
                "rarity": "Легендарный",
                "points_earned": 1000,
                "coins_earned": 50
            }
        },
        "points": 1050,
        "coins": 15,
        "nickname": "Clamsurr",
        "inventory": {
            "luck_booster": 0,
            "time_booster": 0
        },
        "active_luck": false,
        "last_card": "Верой Лечинкель"
    },
    "5402046276": {
        "balance": 0,
        "cards": {
            "Лечинкель Комару": {
                "last_used": 1764176787.4816628,
                "rarity": "Обычный",
                "points_earned": 50,
                "coins_earned": 5
            },
            "Аллах Лечинкель": {
                "last_used": 1764344354.7999063,
                "rarity": "Редкий",
                "points_earned": 250,
                "coins_earned": 15
            }
        },
        "points": 300,
        "coins": 20,
        "nickname": "-| Neax |-",
        "inventory": {
            "luck_booster": 0,
            "time_booster": 0
        },
        "active_luck": false,
        "last_card": "Аллах Лечинкель"
    },
    "5676364226": {
        "balance": 0,
        "cards": {
            "Потужный Лечинкель": {
                "last_used": 1764344271.7165477,
                "rarity": "Эпический",
                "points_earned": 500,
                "coins_earned": 25
            }
        },
        "points": 500,
        "coins": 25,
        "nickname": "Blue_pum",
        "inventory": {
            "luck_booster": 0,
            "time_booster": 0
        },
        "active_luck": false,
        "last_card": "Потужный Лечинкель"
    }
}